LICENCE
MANIFEST.in
README.rst
setup.py
django_starfield/__init__.py
django_starfield/apps.py
django_starfield/widgets.py
django_starfield.egg-info/PKG-INFO
django_starfield.egg-info/SOURCES.txt
django_starfield.egg-info/dependency_links.txt
django_starfield.egg-info/requires.txt
django_starfield.egg-info/top_level.txt
django_starfield/static/django_starfield.css
django_starfield/templates/django_starfield/stars.html
example/manage.py
example/example/__init__.py
example/example/forms.py
example/example/settings.py
example/example/urls.py
example/example/views.py
example/example/wsgi.py
example/example/templates/form.html