Metadata-Version: 1.1
Name: django-starfield
Version: 1.0.post2
Summary: A no-frills Django form widget for rating stars
Home-page: https://edugit.org/AlekSIS/libs/django-starfield
Author: Dominik George
Author-email: dominik.george@teckids.org
License: UNKNOWN
Keywords: django,forms,widget,rating
Platform: UNKNOWN
Classifier: Environment :: Web Environment
Classifier: Framework :: Django
Classifier: Framework :: Django :: 1.11
Classifier: Framework :: Django :: 2.0
Classifier: Framework :: Django :: 2.1
Classifier: License :: OSI Approved :: Apache Software License
Classifier: Operating System :: OS Independent
Classifier: Programming Language :: Python
Classifier: Programming Language :: Python :: 2
Classifier: Programming Language :: Python :: 3
Classifier: Topic :: Internet :: WWW/HTTP
Classifier: Topic :: Internet :: WWW/HTTP :: Dynamic Content
